diffusion/__init__.py
diffusion/exceptions.py
diffusion/py.typed
diffusion/datatypes/__init__.py
diffusion/datatypes/exceptions.py
diffusion/datatypes/raw.py
diffusion/datatypes/complex/__init__.py
diffusion/datatypes/complex/recorddatatype.py
diffusion/datatypes/complex/unknowndatatype.py
diffusion/datatypes/conversion/__init__.py
diffusion/datatypes/conversion/default.py
diffusion/datatypes/foundation/__init__.py
diffusion/datatypes/foundation/abstract.py
diffusion/datatypes/foundation/bytesdatatype.py
diffusion/datatypes/foundation/datatype.py
diffusion/datatypes/foundation/ibytesdatatype.py
diffusion/datatypes/foundation/object.py
diffusion/datatypes/foundation/types.py
diffusion/datatypes/primitives/__init__.py
diffusion/datatypes/primitives/binarydatatype.py
diffusion/datatypes/primitives/doubledatatype.py
diffusion/datatypes/primitives/int64datatype.py
diffusion/datatypes/primitives/jsondatatype.py
diffusion/datatypes/primitives/primitivedatatype.py
diffusion/datatypes/primitives/stringdatatype.py
diffusion/datatypes/timeseries/__init__.py
diffusion/datatypes/timeseries/py.typed
diffusion/datatypes/timeseries/time_series_event.py
diffusion/datatypes/timeseries/time_series_event_metadata.py
diffusion/datatypes/timeseries/types.py
diffusion/features/__init__.py
diffusion/features/control/__init__.py
diffusion/features/control/metrics/__init__.py
diffusion/features/control/metrics/collector.py
diffusion/features/control/metrics/session_metrics.py
diffusion/features/control/metrics/topic_metrics.py
diffusion/features/control/session_trees/__init__.py
diffusion/features/control/session_trees/branch_mapping.py
diffusion/features/control/session_trees/branch_mapping_table.py
diffusion/features/control/session_trees/invalid_branch_mapping_exception.py
diffusion/features/timeseries/__init__.py
diffusion/features/timeseries/query/__init__.py
diffusion/features/timeseries/query/query_result.py
diffusion/features/timeseries/query/range_query.py
diffusion-6.12.1.dist-info/METADATA
diffusion-6.12.1.dist-info/WHEEL
diffusion-6.12.1.dist-info/top_level.txt
diffusion-6.12.1.dist-info/RECORD
