Metadata-Version: 2.1
Name: diffusion
Version: 6.12.1
Summary: Python SDK for Diffusion.
Author-email: DiffusionData Limited <contact@diffusiondata.com>
License: LicenseRef-Proprietary
Project-URL: homepage, https://www.diffusiondata.com/
Keywords: diffusion,cloud,websockets,data
Classifier: Environment :: Other Environment
Classifier: Development Status :: 5 - Production/Stable
Requires-Python: <3.13,>=3.8
Requires-Dist: attrs<24.0,>=21.4.0
Requires-Dist: cbor2==5.*,>=5.1.2
Requires-Dist: stringcase==1.*,>=1.2.0
Requires-Dist: structlog==21.*,>=21.5.0
Requires-Dist: typing-extensions==4.*,>=4.0.1
Requires-Dist: pydantic!=1.10.20,<3.0.0,>=1.9.0
Requires-Dist: diffusion-core==0.*,>=0.0.68
Requires-Dist: aiohttp==3.*,>=3.6.2; python_version < "3.12"
Requires-Dist: aiohttp==3.*,>=3.9.0; python_version >= "3.12"
